{
  "search_metadata": {
    "id": "6861d579d6eb727d70e4181b",
    "status": "Success",
    "json_endpoint": "https://serpapi.com/searches/ed027fa30369c4f6/6861d579d6eb727d70e4181b.json",
    "created_at": "2025-06-30 00:08:25 UTC",
    "processed_at": "2025-06-30 00:08:25 UTC",
    "google_url": "https://www.google.com/search?q=site%3Asummacare.com+%22PROVIDER+DIRECTORY%22++%22FHIR%22+-fire.ly+-linkedin.com+-google.com&oq=site%3Asummacare.com+%22PROVIDER+DIRECTORY%22++%22FHIR%22+-fire.ly+-linkedin.com+-google.com&uule=w+CAIQICINVW5pdGVkIFN0YXRlcw&hl=en&gl=us&num=10&safe=active&sourceid=chrome&ie=UTF-8",
    "raw_html_file": "https://serpapi.com/searches/ed027fa30369c4f6/6861d579d6eb727d70e4181b.html",
    "total_time_taken": 2.73
  },
  "search_parameters": {
    "engine": "google",
    "q": "site:summacare.com \"PROVIDER DIRECTORY\"  \"FHIR\" -fire.ly -linkedin.com -google.com",
    "location_requested": "United States",
    "location_used": "United States",
    "google_domain": "google.com",
    "hl": "en",
    "gl": "us",
    "safe": "active",
    "num": "10",
    "device": "desktop"
  },
  "search_information": {
    "query_displayed": "site:summacare.com \"PROVIDER DIRECTORY\" \"FHIR\" -fire.ly -linkedin.com -google.com",
    "total_results": 0,
    "time_taken_displayed": 0.12,
    "organic_results_state": "Fully empty",
    "query_feedback": {
      "title": "Your search did not match any documents"
    }
  },
  "error": "Google hasn't returned any results for this query."
}